LICENSE
MANIFEST.in
README.rst
setup.py
bin/search-Clipboard
searchClipboard/__init__.py
searchClipboard/core.py
searchClipboard.egg-info/PKG-INFO
searchClipboard.egg-info/SOURCES.txt
searchClipboard.egg-info/dependency_links.txt
searchClipboard.egg-info/requires.txt
searchClipboard.egg-info/top_level.txt