Metadata-Version: 1.0
Name: searchClipboard
Version: 0.1.1
Summary: search google for current clipboard contents
Home-page: https://github.com/AashrayAnand/searchClipboard
Author: Aashray Anand
Author-email: aashrayanand01@gmail.com
License: Copyright (c) 2017, Kenneth Reitz
